{"Added":[],"Modified":[{"Id":50603,"Kind":11,"Name":"EventSubs","Namespace":""},{"Id":50604,"Kind":11,"Name":"DHX Data Handler","Namespace":""},{"Kind":19,"Name":"DHXProjectScheduleAddin","Namespace":""},{"Id":50630,"Kind":12,"Name":"Day Tasks","Namespace":""},{"Id":50610,"Kind":10,"Name":"Day Tasks","Namespace":""},{"Id":50610,"Kind":11,"Name":"Day Tasks Mgt.","Namespace":""}],"Removed":[{"Id":50620,"Kind":16,"Name":"Work-Hour Templates Ext","Namespace":""},{"Id":50620,"Kind":17,"Name":"Work-Hour Template Ext","Namespace":""},{"Id":50612,"Kind":11,"Name":"General Planning Utilities","Namespace":""}]}